lfudacache/__init__.py
lfudacache/__meta__.py
lfudacache/tests.py
lfudacache/utils.py
lfudacache-0.0.2.dist-info/LICENSE
lfudacache-0.0.2.dist-info/METADATA
lfudacache-0.0.2.dist-info/WHEEL
lfudacache-0.0.2.dist-info/top_level.txt
lfudacache-0.0.2.dist-info/zip-safe
lfudacache-0.0.2.dist-info/RECORD
