Metadata-Version: 2.1
Name: lfudacache
Version: 0.0.2
Summary: Less Frequently Used with Dynamic Aging
Home-page: https://gitlab.com/ergoithz/lfudacache
Author: Felipe A. Hernandez
Author-email: ergoithz@gmail.com
License: MIT
Keywords: cache,memoize
Platform: any
Classifier: Development Status :: 4 - Beta
Classifier: License :: OSI Approved :: MIT License
Classifier: Operating System :: OS Independent
Classifier: Programming Language :: Python
Classifier: Programming Language :: Python :: 3
